{
  "FormatType": 1,
  "DeckId": 8913902916,
  "Name": "1",
  "HeroCardId": "HERO_02a",
  "CardIds": [
    "SCH_427",
    "SCH_427",
    "TOY_508",
    "FP1_025",
    "FP1_025",
    "TSC_637",
    "TSC_637",
    "GDB_451",
    "GDB_451",
    "CS2_038",
    "JAM_013",
    "SW_025",
    "CS2_045",
    "CS2_045",
    "CFM_696",
    "CFM_696",
    "TOY_507",
    "TOY_507",
    "CORE_EX1_259",
    "GVG_029",
    "GVG_029",
    "DAL_052",
    "DAL_052",
    "BOT_099",
    "TSC_639",
    "WW_440",
    "WW_382",
    "WW_382",
    "OG_042",
    "TID_712"
  ]
}